{
  "appPageId" : "83ca77eb-662f-4b06-8918-119a00e5bdfb",
  "componentName" : "siteforce:sldsOneColLayout",
  "dataProviders" : [ ],
  "id" : "746180a1-722c-4465-b904-afc1d82e37d8",
  "label" : "Forgot Password",
  "regions" : [ {
    "components" : [ {
      "componentAttributes" : {
        "richTextValue" : "<p style=\"text-align: center;\"><span style=\"color: rgb(255, 255, 255); font-size: 22px;\">PASSWORD RESET</span></p>"
      },
      "componentName" : "forceCommunity:richTextInline",
      "id" : "38cbcf11-ae60-45c9-a761-b0fe5772abdf",
      "renderPriority" : "NEUTRAL",
      "renditionMap" : { },
      "type" : "component"
    }, {
      "componentAttributes" : {
        "richTextValue" : "<p style=\"text-align: center;\"><span style=\"color: rgb(255, 255, 255);\">To reset your password, we'll need your username.</span></p><p style=\"text-align: center;\"><span style=\"color: rgb(255, 255, 255);\"> We'll send password reset instructions to the email address associated with your account.</span></p>"
      },
      "componentName" : "forceCommunity:richTextInline",
      "id" : "7403f2b0-8dae-4e21-8069-0e504c05c0db",
      "renderPriority" : "NEUTRAL",
      "renditionMap" : { },
      "type" : "component"
    }, {
      "componentAttributes" : {
        "checkEmailUrl" : "./CheckPasswordResetEmail",
        "submitButtonLabel" : "Reset Password",
        "usernameLabel" : "Username"
      },
      "componentName" : "salesforceIdentity:forgotPassword2",
      "id" : "734c1254-16fb-45b4-ac32-3ac9a5b37e70",
      "renderPriority" : "NEUTRAL",
      "renditionMap" : { },
      "type" : "component"
    }, {
      "componentAttributes" : {
        "richTextValue" : "<div style=\"text-align: center;\"><a href=\"./\">Cancel</a></div>"
      },
      "componentName" : "forceCommunity:richTextInline",
      "id" : "8a89a293-f752-4532-8501-ae0ee9b8be11",
      "renderPriority" : "NEUTRAL",
      "renditionMap" : { },
      "type" : "component"
    } ],
    "id" : "e1bcb92e-b64d-40cc-998e-4ab61314a33d",
    "regionName" : "content",
    "type" : "region"
  }, {
    "components" : [ {
      "componentAttributes" : {
        "customHeadTags" : "",
        "description" : "",
        "title" : "Forgot Password"
      },
      "componentName" : "forceCommunity:seoAssistant",
      "id" : "60a69da7-101b-4cb8-b321-34ca1e85efb5",
      "renditionMap" : { },
      "type" : "component"
    } ],
    "id" : "5e7ae61a-b34f-4342-9a62-2f0918d4f3a5",
    "regionName" : "sfdcHiddenRegion",
    "type" : "region"
  } ],
  "themeLayoutType" : "Login",
  "type" : "view",
  "viewType" : "forgot-password"
}